pytest_vagrant/__init__.py
pytest_vagrant/errors.py
pytest_vagrant/fixtures.py
pytest_vagrant/machine.py
pytest_vagrant/machine_factory.py
pytest_vagrant/machine_status.py
pytest_vagrant/parse.py
pytest_vagrant/parse_format.py
pytest_vagrant/runresult.py
pytest_vagrant/shell.py
pytest_vagrant/ssh.py
pytest_vagrant/ssh_config.py
pytest_vagrant/ssh_connection.py
pytest_vagrant/vagrant.py
pytest_vagrant-2.1.0.dist-info/LICENSE.rst
pytest_vagrant-2.1.0.dist-info/METADATA
pytest_vagrant-2.1.0.dist-info/WHEEL
pytest_vagrant-2.1.0.dist-info/entry_points.txt
pytest_vagrant-2.1.0.dist-info/top_level.txt
pytest_vagrant-2.1.0.dist-info/RECORD
