Metadata-Version: 2.1
Name: pytest-vagrant
Version: 2.1.0
Summary: A py.test plugin providing access to vagrant.
Home-page: https://github.com/steinwurf/pytest-vagrant
Author: Steinwurf ApS
Author-email: contact@steinwurf.com
License: BSD 3-clause "New" or "Revised" License
Keywords: pytest py.test testing unit tests plugin vagrant
Platform: UNKNOWN
Classifier: Framework :: Pytest
Classifier: Development Status :: 5 - Production/Stable
Classifier: Environment :: Plugins
Classifier: Intended Audience :: Developers
Classifier: License :: OSI Approved :: BSD License
Classifier: Operating System :: OS Independent
Classifier: Programming Language :: Python
Classifier: Programming Language :: Python :: 2
Classifier: Programming Language :: Python :: 3
Classifier: Topic :: Software Development
Classifier: Topic :: Software Development :: Testing
License-File: LICENSE.rst
Requires-Dist: pytest
Requires-Dist: paramiko
Requires-Dist: python-slugify
